{"web":{"client_id":"382294503807-gngc4rgn3g484lqiqrid2m5ansgm8p97.apps.googleusercontent.com","project_id":"eminent-booking-288013","auth_uri":"https://accounts.google.com/o/oauth2/auth","token_uri":"https://oauth2.googleapis.com/token","auth_provider_x509_cert_url":"https://www.googleapis.com/oauth2/v1/certs","client_secret":"nIFxcoBtjzFEv0mYVMgAloIC","redirect_uris":["http://127.0.0.1:55179/authorize/","http://localhost:8080/","https://localhost:44333/","http://localhost:8080/Callback","https://localhost:44333/Callback","http://127.0.0.1:54968/authorize/","https://127.0.0.1:54968/authorize/","http://127.0.0.1:54968/authorize"],"javascript_origins":["http://localhost","https://localhost"]}}